Workbook

Sheet REMUNERACIONES
A1: REMUNERACIONES, HONORARIOS E INCENTIVOS
B3: HONORARIOS | C3: INCENTIVOS | D3: REMUNERACIONES | F3: DEDICACION | G3: MESES A | H3: TOTAL
A4: ITEM | B4: J. COMPLETA | C4: J. COMPLETA | D4: J. COMPLETA | E4: SUBTOTAL | F4: AL PROYECTO | G4: CONTRATAR | H4: PROYECTO
B5: M$/MES | C5: M$/MES | D5: M$/MES | E5: M$/MES | F5: % DE JORNADA | G5: Nº | H5: M$
A6: Profesionales
A7: Jefe de Proyecto / Scrum Master / Líder QA | D7: 2500000 | E7: 2500000 | F7: 0.8 | G7: 4 | H7: 8000000
A8: PO / Líder Gestión y Calidad | D8: 2200000 | E8: 2200000 | F8: 0.8 | G8: 4 | H8: 7040000
A9: Desarrollador Fullstack | D9: 2200000 | E9: 2200000 | F9: 1 | G9: 4 | H9: 8800000
A10: Líder Técnico | D10: 2200000 | E10: 2200000 | F10: 1 | G10: 4 | H10: 8800000
A11: Soporte continuo | D11: 1000000 | E11: 1000000 | F11: 1 | G11: 12 | H11: 0
A12: SUBTOTAL | H12: =SUM(H6:H11)

Sheet EQUIPOS E INFRAESTRUCTURA
A1: EQUIPOS
C3: COSTO | D3: UNITARIO | E3: CANTIDAD | F3: COSTO
A4: NOMBRE DEL EQUIPO | B4: DESCRIPCIÓN | C4: CASO ADQUISICIONES | D4: CASO ARRIENDO O USO | E4: UNIDADES | F4: TOTAL
C5: M$/UNIDAD | D5: UNIDADES EXISTENTES (M$/MES) | E5: O MESES | F5: M$
A6: nn | B6: nn | C6: 0 | D6: 0 | E6: 0 | F6: =(+C6+D6)*E6
F7: =(+C7+D7)*E7
F8: =(+C8+D8)*E8
F9: =(+C9+D9)*E9
F10: =(+C10+D10)*E10
F11: =(+C11+D11)*E11
F12: =(+C12+D12)*E12
A13: SUBTOTAL | F13: =SUM(F6:F12)
A17: INFRAESTRUCTURA
C19: COSTO | D19: UNITARIO | E19: CANTIDAD | F19: COSTO
A20: NOMBRE DE LA INFRAESTRUCTURA | B20: DESCRIPCIÓN | C20: CASO ADQUISICIONES | D20: CASO ARRIENDO O USO | E20: UNIDADES | F20: TOTAL
C21: O HABILITACIÓNM$/UNIDAD | D21: UNIDADES EXISTENTES (M$/MES) | E21: O MESES | F21: M$
A22: Dominio y SSL | B22: Asegura el acceso web y protege la información con cifrado. | D22: 20000 | E22: 12 | F22: =(+C22+D22)*E22
F23: =(+C23+D23)*E23
F24: =(+C24+D24)*E24
F25: =(+C25+D25)*E25
F26: =(+C26+D26)*E26
F27: =(+C27+D27)*E27
F28: =(+C28+D28)*E28
F29: =(+C29+D29)*E29
A30: SUBTOTAL | F30: =SUM(F22:F29)

Sheet SOFTWARE Y FUNGIBLES
A1: SOFTWARE
B3: COSTO | D3: COSTO
A4: DESCRIPCIÓN | B4: UNITARIO | C4: CANTIDAD | D4: TOTAL
B5: M$/UNIDAD | D5: M$
A6: Licencias Open Source (Python, Django, MySQL, Bootstrap, Git) | B6: 0 | C6: 1 | D6: =+B6*C6
A7: Herramientas colaborativas y gestión ágil (Jira) | B7: 0 | C7: 1 | D7: =+B7*C7
D8: =+B8*C8
D9: =+B9*C9
D10: =+B10*C10
D11: =+B11*C11
D12: =+B12*C12
D13: =+B13*C13
D14: =+B14*C14
D15: =+B15*C15
A16: SUBTOTAL | D16: =SUM(D6:D15)
A22: FUNGIBLES
B24: COSTO | D24: COSTO
A25: DESCRIPCIÓN | B25: UNITARIO | C25: CANTIDAD | D25: TOTAL
B26: M$/UNIDAD | D26: M$
A27: Ticket de prueba | B27: 10000 | C27: 5 | D27: =+B27*C27
A28: Papelería | B28: 5000 | C28: 20 | D28: =+B28*C28
D30: =+B30*C30
D31: =+B31*C31
D32: =+B32*C32
D33: =+B33*C33
D34: =+B34*C34
D35: =+B35*C35
D36: =+B36*C36
D37: =+B37*C37
D38: =+B38*C38
D39: =+B39*C39
D40: =+B40*C40
D41: =+B41*C41
A42: SUBTOTAL | D42: =SUM(D27:D41)

Sheet OTROS
A2: PROPIEDAD INTELECTUAL
B4: COSTO | D4: COSTO
A5: DESCRIPCIÓN | B5: UNITARIO | C5: CANTIDAD | D5: TOTAL
B6: M$/UNIDAD | D6: M$
A7: Reserva de derechos del sistema | B7: 26000 | C7: 1 | D7: =+B7*C7
D8: =+B8*C8
D9: =+B9*C9
A10: SUBTOTAL | D10: =SUM(D7:D9)
A13: GASTOS GENERALES E IMPREVISTOS
B15: COSTO | D15: COSTO
A16: DESCRIPCIÓN | B16: UNITARIO | C16: CANTIDAD | D16: TOTAL
B17: M$/UNIDAD | D17: M$
A18: Contingencia general (5%) | B18: =SUM(TOTAL!B7:B12)*5% | C18: 1 | D18: =+B18*C18
D19: =+B19*C19
D20: =+B20*C20
D21: =+B21*C21
A22: SUBTOTAL | D22: =SUM(D18:D21)
A28: GASTOS COMUNES
B30: COSTO | D30: COSTO
A31: DESCRIPCIÓN | B31: UNITARIO | C31: CANTIDAD | D31: TOTAL
B32: M$/UNIDAD | D32: M$
A33: Electricidad | B33: 50000 | C33: 4 | D33: =+B33*C33
A34: Agua potable | B34: 30000 | C34: 4 | D34: =+B34*C34
A35: Internet | B35: 25000 | C35: 4 | D35: =+B35*C35
D36: =+B36*C36
A37: SUBTOTAL | D37: =SUM(D33:D36)
A45: GASTOS DE ADMINISTRACIÓN SUPERIOR
B47: COSTO | D47: COSTO
A48: DESCRIPCIÓN | B48: UNITARIO | C48: CANTIDAD | D48: TOTAL
B49: M$/UNIDAD | D49: M$
D50: =+B50*C50
D51: =+B51*C51
A52: SUBTOTAL | D52: =SUM(D50:D51)

Sheet TOTAL
A1: COSTO TOTAL DEL PROYECTO
B4: COSTO
A5: ITEM | B5: TOTAL
B6: M$
A7: HONORARIOS, INCENTIVOS, REMUNERACIONES | B7: =REMUNERACIONES!H12
A8: EQUIPOS | B8: ='EQUIPOS E INFRAESTRUCTURA'!F13
A9: INFRAESTRUCTURA | B9: ='EQUIPOS E INFRAESTRUCTURA'!F30
A10: SOFTWARE | B10: ='SOFTWARE Y FUNGIBLES'!D16
A11: PROPIEDAD INTELECTUAL | B11: =OTROS!D10
A12: GASTOS COMUNES | B12: =OTROS!D37
A13: GASTOS GENERALES E IMPREVISTOS | B13: =OTROS!D22
A14: TOTAL | B14: =SUM(B7:B13)

Sheet Beneficio (Ventas)
B1: BENEFICIO (VENTAS) ESPERADAS DEL PROYECTO
C3: Años
B4: Períodos de estudio económico | C4: 1 | D4: 2 | E4: 3
B5: Proyeccion de mejora anual | C5: 0.1 | D5: 0.1 | E5: 0.1
B6: Precio unitario | C6: 30000000 | D6: =C6*10%+C6 | E6: =D6*10%+D6
B7: Ingresos | C7: =+C6+C5 | D7: =+D6+D5 | E7: =+E6+E5

Sheet Costos Operación
A1: COSTOS DE OPERACIÓN DEL PROYECTO
A3: Costos de Operación
A5: Año Operación | B5: 1 | C5: 2 | D5: 3
A6: Costo Variable | B6: =C21 | C6: =B6*20%+B6 | D6: =C6*20%+C6
A7: Costos fijos | B7: =C16 | C7: =C16 | D7: =C16
A8: Costos Totales | B8: =SUM(B6:B7) | C8: =SUM(C6:C7) | D8: =SUM(D6:D7)
A11: Costo Fijo | B11: Honorarios, incentivos, remuneraciones | C11: 12000000
B12: Software
B13: Seuro Inventario
B14: Seguridad
B15: Personal
C16: =SUM(C11:C15)
A17: Costo Variable | B17: Propiedad intelectual | C17: 26000
B18: gastos comunes | C18: 420000
B19: gastos Imprevistos | C19: 1666300
C21: =SUM(C17:C20)

Sheet Inversiones
E1: INVERSIONES A REALIZAR EN PROYECTO
B3: Inversiones
B5: Item | C5: Cantidad | D5: Costo CLP$ | E5: Costo Total CLP$
B6: Desarrollo Software | C6: 4 | D6: 32640000 | E6: =D6 | H6: Depreciación | I6: (Costo – valor de desecho)/Años de vida útil
B7: Infraestructura Tecnologica | C7: 0 | D7: 0 | E7: =D7
B8: Implementación Sistema | C8: 1 | D8: 100000 | E8: =D8
B9: Invers. Cap. Tª. | C9: 1 | D9: 100000 | E9: =D9 | H9: Activos | I9: =+E7
B10: Costos Totales | D10: =SUM(D6:D9) | E10: =SUM(E6:E9) | H10: Valor residual | I10: =+I9*20% | J10: = Valor Desecho | K10: =+E7*20%
H11: Vida útil (años) | I11: 3
H13: Depreciación | I13: =+(I9-I10)/I11

Sheet Préstamo
E1: CALCULO DE CUOTA ANUAL PRÉSTAMO BANCARIO
B2: Inversión en activos | C2: 32840000
B3: Préstamo 75% Inversión | C3: =+C2*75%
B4: Interés | C4: 0.09 | D4: (Tasa Prestamo Comercial)
B5: Cuotas | C5: 3 | E5: Valor Cuota | F5: =PMT(C4,C5,-C3) | I5: http://simuladorcreditos.cl/
B7: CALCULO CUOTA PRÉSTAMO (AMORTIZACIÓN) | H7: Determinación cuota préstamo:
B8: R = P [(i (1 + i)n) / ((1 + i)n – 1)] | H8: Año | I8: Saldo Capital | J8: Interés | K8: Cuota | M8: Capital pagado
H9: 0 | I9: =C3 | M9: 0
H10: 1 | I10: =+I9-L10 | J10: =+I9*$C$4 | K10: =$F$5 | L10: =+K10-J10 | M10: =+L10
H11: 2 | I11: =+I10-L11 | J11: =+I10*$C$4 | K11: =$F$5 | L11: =+K11-J11 | M11: =+M10+L11
E12: Valor Cuota anual | F12: =F5 | H12: 3 | I12: =+I11-L12 | J12: =+I11*$C$4 | K12: =$F$5 | L12: =+K12-J12 | M12: =+M11+L12
B13: R = renta (cuota) | H13: La cuota del Banco tiene una parte de interés y otra de amortización del capital real que se pidió como préstamo. En tabla superior se aclara como está compuesta la cuota bancaria y que parte corresponde a interés y que parte amortización del saldo capital real. Fijarse que para determinar interés calculo sobre el capita real (27.750.000) el interés que es 18%. Luego su resultado restado al valor cuota me entrega el valor de recuperación de capital. Posteriormente, se realiza la misma operación con el saldo que queda por analizar.
B14: P = Monto Principal (préstamo adquirido)
B15: i = tasa de interés
B16: n = Períodos de cuotas (años/meses, según corresponda)

Sheet Flujo de Caja
B1: FLUJO DE CAJA
B3: ítem | C3: Año 0 | D3: Año 1 | E3: Año 2 | F3: Año 3 | H3: PAY BACK
B4: Beneficio (Ventas) | D4: ='Beneficio (Ventas)'!C7 | E4: ='Beneficio (Ventas)'!D7 | F4: ='Beneficio (Ventas)'!E7 | H4: Item | I4: Año 0 | J4: Año 1 | K4: Año 2 | L4: Año 3
H5: Flujo de Caja | I5: =C23 | J5: =D23 | K5: =E23 | L5: =F23
B6: Costos Operación | D6: =-'Costos Operación'!B8 | E6: =-'Costos Operación'!C8 | F6: =-'Costos Operación'!D8 | J6: =I5+J5
B7: Depreciación | D7: =-Inversiones!$I$13 | E7: =-Inversiones!$I$13 | F7: =-Inversiones!$I$13 | K7: =J6+K5
L8: =K7+L5
B9: Interés por Préstamo | D9: =-Préstamo!J10 | E9: =-Préstamo!J11 | F9: =-Préstamo!J12
B10: Utilid. antes Impto. | D10: =SUM(D4:D9) | E10: =SUM(E4:E9) | F10: =SUM(F4:F9)
B11: 27% Impuesto | D11: =-IF(D10=0,0,D10*27%) | E11: =-IF(E10=0,0,E10*27%) | F11: =-IF(F10=0,0,F10*27%)
B12: Utilid. desp. Impto. | D12: =SUM(D10:D11) | E12: =SUM(E10:E11) | F12: =SUM(F10:F11)
B13: Depreciación | D13: =-D7 | E13: =-E7 | F13: =-F7 | I13: INDICADORES
B14: Amortización préstamo | D14: =-Préstamo!L10 | E14: =-Préstamo!L11 | F14: =-Préstamo!L12 | I14: VAN | J14: =I23
B15: Préstamo (75% inversión) | C15: =Préstamo!C3 | I15: TIR | J15: =I24
B16: Inversiones: | I16: Tasa de dcto. | J16: 0.12 | K16: (Para Tecnología)
B17: Desarrollo Software | C17: =-Inversiones!E6 | I17: Horizonte | J17: 3
B18: Infraestructura Tecnologica | C18: =-Inversiones!E7 | I18: Payback | J18: 2.56
B19: Implementación Sistema | C19: =-Inversiones!E8
B20: Invers. Cap. Tª. | C20: =-Inversiones!E9
B21: Valor Residual | F21: =Inversiones!K10
B22: Recuperac. Cap.Tª | F22: =Inversiones!E9
B23: Flujo de Caja | C23: =SUM(C12:C22) | D23: =SUM(D12:D22) | E23: =SUM(E12:E22) | F23: =SUM(F12:F22) | H23: VAN | I23: =NPV(0.12,D23:F23)-C23
H24: TIR | I24: =IRR(C23:F23)
B25: PARA CALCULO MANUAL DE VAN | C25: =+C23 | D25: =+D23/((1+$J$16)^1) | E25: =+E23/((1+$J$16)^2) | F25: =+F23/((1+$J$16)^3)
F26: =SUM(C25:F25)
